easyMirai/__init__.py
easyMirai/__main__.py
easyMirai/__version__.py
easyMirai/actionType.py
easyMirai/eventType.py
easyMirai/getType.py
easyMirai/method.py
easyMirai/sendType.py
easyMirai/setType.py
easyMirai/uploadType.py
easyMirai/data/__init__.py
easyMirai/data/expand.json
easyMirai/data/getData.py
easyMirai/data/models.json
easyMirai/echo/__init__.py
easyMirai/echo/echoTypeMode.py
easyMirai-2.34.36.dist-info/LICENSE
easyMirai-2.34.36.dist-info/LICENSE.md
easyMirai-2.34.36.dist-info/METADATA
easyMirai-2.34.36.dist-info/WHEEL
easyMirai-2.34.36.dist-info/top_level.txt
easyMirai-2.34.36.dist-info/RECORD
