Metadata-Version: 2.1
Name: easyMirai
Version: 2.34.36
Summary: 帮助QBot开发者快速构建简单的QQ机器人
Home-page: https://github.com/easyMirais/easyMirai
Author: ExMikuPro & HexMikuMax
Author-email: sfnco-miku@outlook.com
License: GNU
Platform: UNKNOWN
Classifier: License :: OSI Approved :: MIT License
Classifier: Programming Language :: Python
Classifier: Programming Language :: Python :: 3
Classifier: Programming Language :: Python :: 3.6
Classifier: Programming Language :: Python :: 3.7
Classifier: Programming Language :: Python :: 3.8
Classifier: Programming Language :: Python :: 3.9
Classifier: License :: OSI Approved :: GNU General Public License v3 (GPLv3)
Requires-Python: >=3.6.0
Requires-Dist: requests
Requires-Dist: rich
Requires-Dist: urllib3 (==1.26.2)
